besiktas/__init__.py
besiktas/cli.py
besiktas/scrapper.py
besiktas/screen.py
besiktas-0.1.12.dist-info/LICENSE.txt
besiktas-0.1.12.dist-info/METADATA
besiktas-0.1.12.dist-info/WHEEL
besiktas-0.1.12.dist-info/entry_points.txt
besiktas-0.1.12.dist-info/RECORD
