Metadata-Version: 2.1
Name: besiktas
Version: 0.1.12
Summary: besiktas cli!
Home-page: https://github.com/osmanuygar/besiktas
License: MIT
Keywords: besiktas
Author: uygar
Author-email: osmanuygar@gmail.com
Requires-Python: >=3.9,<4.0
Classifier: Development Status :: 4 - Beta
Classifier: Environment :: Console
Classifier: License :: OSI Approved :: MIT License
Classifier: Operating System :: OS Independent
Classifier: Programming Language :: Python :: 3
Classifier: Programming Language :: Python :: 3.9
Classifier: Programming Language :: Python :: 3.10
Classifier: Programming Language :: Python :: 3.11
Classifier: Programming Language :: Python :: 3 :: Only
Classifier: Programming Language :: Python :: 3.6
Classifier: Programming Language :: Python :: 3.7
Classifier: Programming Language :: Python :: 3.8
Requires-Dist: beautifulsoup4 (>=4.11.1,<5.0.0)
Requires-Dist: requests (>=2.28.1,<3.0.0)
Requires-Dist: rich (>=12.6.0,<13.0.0)
Project-URL: Repository, https://github.com/osmanuygar/besiktas
